LICENSE
MANIFEST.in
README.rst
setup.py
uaverify/__about__.py
uaverify/__init__.py
uaverify/androidsupport.py
uaverify/iossupport.py
uaverify/package_info.py
uaverify/support.py
uaverify/ua_inspection.cfg
uaverify/uainspector.py
uaverify.egg-info/PKG-INFO
uaverify.egg-info/SOURCES.txt
uaverify.egg-info/dependency_links.txt
uaverify.egg-info/entry_points.txt
uaverify.egg-info/top_level.txt