Metadata-Version: 1.0
Name: uaverify
Version: 0.7.4
Summary: Urban Airship Build Verification
Home-page: https://github.com/urbanairship/powercar
Author: Urban Airship
Author-email: support@urbanairship.com
License: APLv2
Platform: UNKNOWN
